adb.py
lsh_adb-1.0.dist-info/METADATA
lsh_adb-1.0.dist-info/WHEEL
lsh_adb-1.0.dist-info/top_level.txt
lsh_adb-1.0.dist-info/RECORD
