Metadata-Version: 2.1
Name: lsh_adb
Version: 1.0
Summary: A tool for adb
Author: Waton
